README.md
setup.py
molick/__init__.py
molick.egg-info/PKG-INFO
molick.egg-info/SOURCES.txt
molick.egg-info/dependency_links.txt
molick.egg-info/top_level.txt