Metadata-Version: 1.1
Name: molick
Version: 0.0.0
Summary: Hacker's exclusive library
Home-page: https://github.com/molick-tech/molick
Author: yourmoln
Author-email: yourmoln@outlook.com
License: UNKNOWN
Platform: UNKNOWN
Classifier: Development Status :: 3 - Alpha
Classifier: License :: OSI Approved :: Apache Software License
Classifier: Programming Language :: Python :: 3
